{
  "appData": {
    "version": "1.0.14",
    "date": "2019-4-4",
    "isForceUpdate": false,
    "infomation": "更新说明"
  },
  "index": "/index.html",
  "assetGroups": [{
    "name": "app",
    "installMode": "prefetch",
    "resources": {
      "files": [
        "/favicon.ico",
        "/index.html",
        "/*.css",
        "/*.js"
      ]
    }
  }, {
    "name": "assets",
    "installMode": "lazy",
    "updateMode": "prefetch",
    "resources": {
      "files": [
        "/assets/**",
        "/*.(eot|svg|cur|jpg|png|webp|gif|otf|ttf|woff|woff2|ani)"
      ]
    }
  }]
}
